pes-innovation-lab-hunt/__init__.py
pes-innovation-lab-hunt/hunt.py
pes_innovation_lab_hunt/__init__.py
pes_innovation_lab_hunt/hunt.py
pes_innovation_lab_hunt-1.3.dist-info/METADATA
pes_innovation_lab_hunt-1.3.dist-info/WHEEL
pes_innovation_lab_hunt-1.3.dist-info/top_level.txt
pes_innovation_lab_hunt-1.3.dist-info/RECORD
