Metadata-Version: 2.1
Name: pes-innovation-lab-hunt
Version: 1.3
Summary: 2024 Hunt package
Author: PES Innovation Lab
Author-email: innovationlab@pes.edu
